sublyme/embeddings.py
sublyme/sublyme.py
sublyme/models/lysin_miner.pkl
sublyme/models/val_endo_clf.pkl
sublyme-1.2.1.dist-info/METADATA
sublyme-1.2.1.dist-info/WHEEL
sublyme-1.2.1.dist-info/entry_points.txt
sublyme-1.2.1.dist-info/licenses/LICENSE
sublyme-1.2.1.dist-info/RECORD
